flapgui/__init__.py
flapgui-0.5.0.dist-info/LICENSE
flapgui-0.5.0.dist-info/METADATA
flapgui-0.5.0.dist-info/WHEEL
flapgui-0.5.0.dist-info/top_level.txt
flapgui-0.5.0.dist-info/RECORD
