Metadata-Version: 2.1
Name: flapgui
Version: 0.5.0
Summary: Easy-to-use and cross-platform GUI library for making functional GUI apps
Author-email: WinFan3672 <winfan3672@gmail.com>
Project-URL: Homepage, https://github.com/WinFan3672/Flap
Project-URL: Bug Tracker, https://github.com/WinFan3672/Flap/issues
Classifier: Programming Language :: Python :: 3
Classifier: License :: OSI Approved :: MIT License
Classifier: Operating System :: OS Independent
Requires-Python: >=3.7
License-File: LICENSE
